healthcheck/__init__.py
healthcheck/healthcheck.py
healthcheck/models.py
healthcheck/py.typed
healthcheck/utils.py
python_healthchecklib-0.1.1.dist-info/LICENSE
python_healthchecklib-0.1.1.dist-info/WHEEL
python_healthchecklib-0.1.1.dist-info/METADATA
python_healthchecklib-0.1.1.dist-info/RECORD
