Metadata-Version: 2.1
Name: python-healthchecklib
Version: 0.1.1
Summary: Opinionated healthcheck library
Home-page: https://github.com/HathorNetwork/python-healthcheck-lib/
License: MIT
Author: Hathor Team
Author-email: contact@hathor.network
Requires-Python: >=3.8.1,<4.0.0
Classifier: License :: OSI Approved :: MIT License
Classifier: Programming Language :: Python :: 3
Classifier: Programming Language :: Python :: 3.9
Classifier: Programming Language :: Python :: 3.10
Classifier: Programming Language :: Python :: 3.11
Project-URL: Repository, https://github.com/HathorNetwork/python-healthcheck-lib/
